leidian/__int__.py
leidian/leidna.py
leidian_adb-0.0.1.dist-info/METADATA
leidian_adb-0.0.1.dist-info/WHEEL
leidian_adb-0.0.1.dist-info/top_level.txt
leidian_adb-0.0.1.dist-info/RECORD
