Metadata-Version: 2.1
Name: leidian-adb
Version: 0.0.1
Summary: 雷电模块
Home-page: https://github.com/qxt514657/LdAdb.py.git
Author: 1Q847
Author-email: 976671673@qq.com
License: MIT
Platform: UNKNOWN
